<annotation>
	<folder>All in One</folder>
	<filename>00044.jpg</filename>
	<path>F:\M.Sc\Safari\All in One\00044.jpg</path>
	<source>
		<database>Unknown</database>
	</source>
	<size>
		<width>2560</width>
		<height>1440</height>
		<depth>3</depth>
	</size>
	<segmented>0</segmented>
	<object>
		<name>Headlight</name>
		<pose>Unspecified</pose>
		<truncated>0</truncated>
		<difficult>0</difficult>
		<bndbox>
			<xmin>745</xmin>
			<ymin>695</ymin>
			<xmax>1131</xmax>
			<ymax>787</ymax>
		</bndbox>
	</object>
	<object>
		<name>Grill</name>
		<pose>Unspecified</pose>
		<truncated>0</truncated>
		<difficult>0</difficult>
		<bndbox>
			<xmin>336</xmin>
			<ymin>737</ymin>
			<xmax>703</xmax>
			<ymax>854</ymax>
		</bndbox>
	</object>
	<object>
		<name>Fog Lamp &amp; Scope</name>
		<pose>Unspecified</pose>
		<truncated>0</truncated>
		<difficult>0</difficult>
		<bndbox>
			<xmin>774</xmin>
			<ymin>897</ymin>
			<xmax>981</xmax>
			<ymax>1013</ymax>
		</bndbox>
	</object>
	<object>
		<name>Front Bumper</name>
		<pose>Unspecified</pose>
		<truncated>0</truncated>
		<difficult>0</difficult>
		<bndbox>
			<xmin>291</xmin>
			<ymin>866</ymin>
			<xmax>1127</xmax>
			<ymax>1058</ymax>
		</bndbox>
	</object>
	<object>
		<name>Front</name>
		<pose>Unspecified</pose>
		<truncated>0</truncated>
		<difficult>0</difficult>
		<bndbox>
			<xmin>286</xmin>
			<ymin>587</ymin>
			<xmax>1339</xmax>
			<ymax>1063</ymax>
		</bndbox>
	</object>
</annotation>
